itk/ITKClassifiersPython.py
itk/ITKLabelVotingPython.py
itk/ITKRegionGrowingPython.py
itk/ITKSuperPixelPython.py
itk/ITKWatershedsPython.py
itk/_ITKClassifiersPython.abi3.so
itk/_ITKLabelVotingPython.abi3.so
itk/_ITKRegionGrowingPython.abi3.so
itk/_ITKSuperPixelPython.abi3.so
itk/_ITKWatershedsPython.abi3.so
itk/itkBayesianClassifierImageFilterPython.py
itk/itkBayesianClassifierInitializationImageFilterPython.py
itk/itkBinaryMedianImageFilterPython.py
itk/itkConfidenceConnectedImageFilterPython.py
itk/itkConnectedThresholdImageFilterPython.py
itk/itkIsolatedConnectedImageFilterPython.py
itk/itkIsolatedWatershedImageFilterPython.py
itk/itkLabelVotingImageFilterPython.py
itk/itkMorphologicalWatershedFromMarkersImageFilterPython.py
itk/itkMorphologicalWatershedImageFilterPython.py
itk/itkNeighborhoodConnectedImageFilterPython.py
itk/itkSLICImageFilterPython.py
itk/itkScalarImageKmeansImageFilterPython.py
itk/itkTobogganImageFilterPython.py
itk/itkVectorConfidenceConnectedImageFilterPython.py
itk/itkVotingBinaryHoleFillingImageFilterPython.py
itk/itkVotingBinaryImageFilterPython.py
itk/itkVotingBinaryIterativeHoleFillingImageFilterPython.py
itk/itkWatershedImageFilterPython.py
itk/Configuration/ITKClassifiersConfig.py
itk/Configuration/ITKClassifiers_snake_case.py
itk/Configuration/ITKLabelVotingConfig.py
itk/Configuration/ITKLabelVoting_snake_case.py
itk/Configuration/ITKRegionGrowingConfig.py
itk/Configuration/ITKRegionGrowing_snake_case.py
itk/Configuration/ITKSuperPixelConfig.py
itk/Configuration/ITKSuperPixel_snake_case.py
itk/Configuration/ITKWatershedsConfig.py
itk/Configuration/ITKWatersheds_snake_case.py
itk_segmentation.libs/libtbb-3c88584c.so.12.9
itk_segmentation-5.4.4.post1.dist-info/METADATA
itk_segmentation-5.4.4.post1.dist-info/WHEEL
itk_segmentation-5.4.4.post1.dist-info/RECORD
itk_segmentation-5.4.4.post1.dist-info/licenses/LICENSE
itk_segmentation-5.4.4.post1.dist-info/licenses/ITK-source/ITK/LICENSE
itk_segmentation-5.4.4.post1.dist-info/licenses/ITK-source/ITK/NOTICE
